{
  "id": "10001022",
  "appId": "10069865",
  "history": [
    {
      "date": "2026-01-09",
      "count": 0
    },
    {
      "date": "2026-01-10",
      "count": 0
    },
    {
      "date": "2026-01-11",
      "count": 0
    },
    {
      "date": "2026-01-12",
      "count": 0
    },
    {
      "date": "2026-01-13",
      "count": 0
    },
    {
      "date": "2026-01-14",
      "count": 0
    },
    {
      "date": "2026-01-15",
      "count": 0
    },
    {
      "date": "2026-01-16",
      "count": 0
    },
    {
      "date": "2026-01-17",
      "count": 0
    },
    {
      "date": "2026-01-18",
      "count": 0
    },
    {
      "date": "2026-01-19",
      "count": 0
    },
    {
      "date": "2026-01-20",
      "count": 0
    },
    {
      "date": "2026-01-21",
      "count": 0
    },
    {
      "date": "2026-01-22",
      "count": 0
    },
    {
      "date": "2026-01-23",
      "count": 0
    }
  ]
}
