{
  "description": "Category history for app 10165145",
  "history": [
    {
      "date": "2025-06-22",
      "marketplace_category_ids": [
        8,
        6,
        5
      ]
    },
    {
      "date": "2025-06-23",
      "marketplace_category_ids": [
        8,
        6,
        5
      ]
    },
    {
      "date": "2025-06-24",
      "marketplace_category_ids": [
        8,
        6,
        5
      ]
    },
    {
      "date": "2025-06-25",
      "marketplace_category_ids": [
        8,
        6,
        5
      ]
    },
    {
      "date": "2025-06-26",
      "marketplace_category_ids": [
        8,
        6,
        5
      ]
    },
    {
      "date": "2025-06-27",
      "marketplace_category_ids": [
        8,
        6,
        5
      ]
    },
    {
      "date": "2025-06-28",
      "marketplace_category_ids": [
        8,
        6,
        5
      ]
    },
    {
      "date": "2025-06-29",
      "marketplace_category_ids": [
        8,
        6,
        5
      ]
    },
    {
      "date": "2025-06-30",
      "marketplace_category_ids": [
        8,
        6,
        5
      ]
    },
    {
      "date": "2025-07-01",
      "marketplace_category_ids": [
        8,
        6,
        5
      ]
    },
    {
      "date": "2025-07-02",
      "marketplace_category_ids": [
        8,
        6,
        5
      ]
    },
    {
      "date": "2025-07-03",
      "marketplace_category_ids": [
        8,
        6,
        5
      ]
    },
    {
      "date": "2025-07-04",
      "marketplace_category_ids": [
        8,
        6,
        5
      ]
    },
    {
      "date": "2025-07-05",
      "marketplace_category_ids": [
        8,
        6,
        5
      ]
    },
    {
      "date": "2025-07-06",
      "marketplace_category_ids": [
        8,
        6,
        5
      ]
    },
    {
      "date": "2025-07-07",
      "marketplace_category_ids": [
        8,
        6,
        5
      ]
    },
    {
      "date": "2025-07-08",
      "marketplace_category_ids": [
        8,
        6,
        5
      ]
    },
    {
      "date": "2025-07-09",
      "marketplace_category_ids": [
        8,
        6,
        5
      ]
    },
    {
      "date": "2025-07-10",
      "marketplace_category_ids": [
        8,
        6,
        5
      ]
    },
    {
      "date": "2025-07-11",
      "marketplace_category_ids": [
        8,
        6,
        5
      ]
    },
    {
      "date": "2025-07-12",
      "marketplace_category_ids": [
        8,
        6,
        5
      ]
    },
    {
      "date": "2025-07-13",
      "marketplace_category_ids": [
        8,
        6,
        5
      ]
    }
  ]
}
