{
  "description": "Category history for app 10316906",
  "history": [
    {
      "date": "2025-07-02",
      "marketplace_category_ids": [
        10000000,
        9,
        7
      ]
    },
    {
      "date": "2025-07-03",
      "marketplace_category_ids": [
        10000000,
        9,
        7
      ]
    },
    {
      "date": "2025-07-04",
      "marketplace_category_ids": [
        10000000,
        9,
        7
      ]
    },
    {
      "date": "2025-07-05",
      "marketplace_category_ids": [
        10000000,
        9,
        7
      ]
    },
    {
      "date": "2025-07-06",
      "marketplace_category_ids": [
        10000000,
        9,
        7
      ]
    },
    {
      "date": "2025-07-07",
      "marketplace_category_ids": [
        10000000,
        9,
        7
      ]
    }
  ]
}
